duckt/__init__.py
duckt/duck_traverse.py
duckt-0.1.1.dist-info/LICENSE
duckt-0.1.1.dist-info/WHEEL
duckt-0.1.1.dist-info/METADATA
duckt-0.1.1.dist-info/RECORD
