Metadata-Version: 2.1
Name: duckt
Version: 0.1.1
Summary: Python package facilitating duck typing through attribute traverse utilities
Home-page: https://github.com/monomonedula/duckt
License: MIT
Keywords: decorator,duck-typing,ducktyping,wrapper,utility
Author: Vladyslav Halchenko
Author-email: valh@tuta.io
Requires-Python: >=3.6,<4.0
Classifier: License :: OSI Approved :: MIT License
Classifier: Programming Language :: Python :: 3
Classifier: Programming Language :: Python :: 3.6
Classifier: Programming Language :: Python :: 3.7
Classifier: Programming Language :: Python :: 3.8
Project-URL: Repository, https://github.com/monomonedula/duckt
